<?xml version="1.0" encoding="UTF-8"?><record_update table="io_set_item">
    <io_set_item action="INSERT_OR_UPDATE">
        <order>5000</order>
        <sc_cat_item display_value="Meeting &amp; Events Reservation">fdc27c801b71e51080feea02f54bcb3f</sc_cat_item>
        <sys_class_name>io_set_item</sys_class_name>
        <sys_created_by>bassem</sys_created_by>
        <sys_created_on>2023-04-24 20:39:01</sys_created_on>
        <sys_id>118742931b1ee51080feea02f54bcb3b</sys_id>
        <sys_mod_count>2</sys_mod_count>
        <sys_name>Training Information.Room Reservation</sys_name>
        <sys_package display_value="OWS Meet" source="x_g_nioa_ows_meet">c67fe0cc1b31e51080feea02f54bcb32</sys_package>
        <sys_policy/>
        <sys_scope display_value="OWS Meet">c67fe0cc1b31e51080feea02f54bcb32</sys_scope>
        <sys_update_name>io_set_item_118742931b1ee51080feea02f54bcb3b</sys_update_name>
        <sys_updated_by>bassem</sys_updated_by>
        <sys_updated_on>2023-04-24 20:39:16</sys_updated_on>
        <variable_set display_value="Training Information">df2de9d91b71e910fdd8848ce54bcb75</variable_set>
    </io_set_item>
</record_update>
